simplepyged/__init__.py
simplepyged/events.py
simplepyged/gedcom.py
simplepyged/matches.py
simplepyged/records.py
test/__init__.py
test/test_alltags.py
test/test_bom.py
test/test_matches.py
test/test_records.py
test/test_simplepyged.py
simplepyged_ob-0.1.0.dist-info/LICENSE.txt
simplepyged_ob-0.1.0.dist-info/METADATA
simplepyged_ob-0.1.0.dist-info/WHEEL
simplepyged_ob-0.1.0.dist-info/top_level.txt
simplepyged_ob-0.1.0.dist-info/RECORD
