Metadata-Version: 2.1
Name: simplepyged-ob
Version: 0.1.0
Summary: A simple Python GEDCOM parser (forked from gburca/simplepyged which forked from dijxtra/simplepyged)
Home-page: https://github.com/oberron/simplepyged
Author: Oberron (based on original work from Nikola Škorić)
Author-email: one.annum@gmail.com
License: GPL
Keywords: gedcom,genealogy
Classifier: Development Status :: 4 - Beta
Classifier: Intended Audience :: Developers
Classifier: Operating System :: OS Independent
Classifier: Programming Language :: Python
Classifier: Topic :: Sociology :: Genealogy
Classifier: Topic :: Software Development :: Libraries :: Python Modules
License-File: LICENSE.txt
